Metadata-Version: 2.1
Name: example-pkg-Tanyee
Version: 0.0.1
Summary: An example package
Home-page: https://github.com/TanyeeZhang/my-python-demo
Author: Tanyee Zhang
Author-email: author@example.com
License: UNKNOWN
Platform: UNKNOWN
Classifier: Programming Language :: Python :: 3
Classifier: License :: OSI Approved :: MIT License
Classifier: Operating System :: OS Independent
